commandler/__init__.py
commandler/command.py
commandler/example.py
commandler-1.0.4.dist-info/LICENCE
commandler-1.0.4.dist-info/METADATA
commandler-1.0.4.dist-info/WHEEL
commandler-1.0.4.dist-info/top_level.txt
commandler-1.0.4.dist-info/RECORD
